odoo/addons/web_chatter_camera/README.rst
odoo/addons/web_chatter_camera/__init__.py
odoo/addons/web_chatter_camera/__manifest__.py
odoo/addons/web_chatter_camera/i18n/it.po
odoo/addons/web_chatter_camera/i18n/web_chatter_camera.pot
odoo/addons/web_chatter_camera/readme/CONTRIBUTORS.md
odoo/addons/web_chatter_camera/readme/DESCRIPTION.md
odoo/addons/web_chatter_camera/static/description/icon.png
odoo/addons/web_chatter_camera/static/description/index.html
odoo/addons/web_chatter_camera/static/src/components/chatter_topbar/chatter_topbar.esm.js
odoo/addons/web_chatter_camera/static/src/components/chatter_topbar/chatter_topbar.xml
odoo/addons/web_chatter_camera/static/src/components/video_camera/video_camera.esm.js
odoo/addons/web_chatter_camera/static/src/components/video_camera/video_camera.xml
odoo_addon_web_chatter_camera-16.0.1.0.0.4.dist-info/METADATA
odoo_addon_web_chatter_camera-16.0.1.0.0.4.dist-info/WHEEL
odoo_addon_web_chatter_camera-16.0.1.0.0.4.dist-info/top_level.txt
odoo_addon_web_chatter_camera-16.0.1.0.0.4.dist-info/RECORD
